LICENSE.txt
README.md
setup.cfg
setup.py
dn757657_utils.egg-info/PKG-INFO
dn757657_utils.egg-info/SOURCES.txt
dn757657_utils.egg-info/dependency_links.txt
dn757657_utils.egg-info/top_level.txt
dn_docoptutils/__init__.py
dn_docoptutils/docopt_utils.py
dn_fileutils/__init__.py
dn_fileutils/file_utils.py