Metadata-Version: 2.1
Name: dn757657-utils
Version: 0.0.3
Summary: personal utility funcs
Home-page: https://github.com/dn757657/dn_utils.git
Download-URL: https://github.com/dn757657/dnutils/archive/refs/tags/0.0.3.tar.gz
Author: Dan
Author-email: daniel.js.campbell@gmail.com
License: MIT
Keywords: utility
Platform: UNKNOWN
Classifier: Development Status :: 3 - Alpha
Classifier: Intended Audience :: Developers
Classifier: Topic :: Software Development :: Build Tools
Classifier: License :: OSI Approved :: MIT License
Classifier: Programming Language :: Python :: 3
Classifier: Programming Language :: Python :: 3.4
Classifier: Programming Language :: Python :: 3.5
Classifier: Programming Language :: Python :: 3.6
License-File: LICENSE.txt
